MANIFEST.in
README.md
setup.py
revpy/__init__.py
revpy/fare_transformation.py
revpy/helpers.py
revpy/lp_solve.py
revpy/meta_optimizers.py
revpy/mfrm.py
revpy/optimizers.py
revpy/revpy.py
revpy.egg-info/PKG-INFO
revpy.egg-info/SOURCES.txt
revpy.egg-info/dependency_links.txt
revpy.egg-info/top_level.txt